pythontyperlol/__init__.py
pythontyperlol-1.0.0.dist-info/METADATA
pythontyperlol-1.0.0.dist-info/WHEEL
pythontyperlol-1.0.0.dist-info/top_level.txt
pythontyperlol-1.0.0.dist-info/RECORD
